Metadata-Version: 1.1
Name: oktopus
Version: 0.1.dev7
Summary: soft-bodied, eight-armed package for beautiful inference
Home-page: https://github.com/mirca/oktopus
Author: KeplerGO
Author-email: jvmirca@gmail.com
License: MIT
Keywords: statistics probability
Platform: UNKNOWN
Classifier: Development Status :: 3 - Alpha
Classifier: Intended Audience :: Science/Research
Classifier: License :: OSI Approved :: MIT License
Classifier: Programming Language :: Python :: 3.6
